cli/__init__.py
cli/app.py
cli/command_parser.py
cli/config.py
cli/main.py
core/basellm.py
core/basemessage.py
core/basemodel.py
core/baseoutput.py
core/basepermission.py
core/bashcode.py
core/executor/base_executor.py
core/executor/sequential_shell_executor.py
core/executor/simple_executor.py
core/prompts.py
llms/__init__.py
llms/arlillm.py
llms/cerebrasllm.py
llms/googlellm.py
llms/groqllm.py
llms/litellmllm.py
llms/model.py
llms/ollamallm.py
llms/openaillm.py
llms/prompt_builder.py
llms/utils.py
utils/__init__.py
utils/exceptions.py
utils/logger.py
cli_agent-0.1.4.dist-info/METADATA
cli_agent-0.1.4.dist-info/WHEEL
cli_agent-0.1.4.dist-info/entry_points.txt
cli_agent-0.1.4.dist-info/RECORD
