Metadata-Version: 2.1
Name: cli-agent
Version: 0.1.4
Summary: AI for CLI
Author: tikendraw
Author-email: tikendraksahu1029@gmail.com
Requires-Python: >=3.11,<3.13
Classifier: Programming Language :: Python :: 3
Classifier: Programming Language :: Python :: 3.11
Classifier: Programming Language :: Python :: 3.12
Requires-Dist: cerebras-cloud-sdk (>=1.2.0,<2.0.0)
Requires-Dist: click (>=8.1.7,<9.0.0)
Requires-Dist: google-generativeai (>=0.8.0,<0.9.0)
Requires-Dist: groq (>=0.11.0,<0.12.0)
Requires-Dist: litellm (>=1.45.0,<2.0.0)
Requires-Dist: ollama (>=0.3.2,<0.4.0)
Requires-Dist: termcolor (>=2.4.0,<3.0.0)
